easygh/__init__.py
easygh/main.py
easygh-1.0.0.dist-info/METADATA
easygh-1.0.0.dist-info/WHEEL
easygh-1.0.0.dist-info/top_level.txt
easygh-1.0.0.dist-info/RECORD
