Metadata-Version: 2.1
Name: easygh
Version: 1.0.0
Summary: This simple library rates websites based on various factors
Home-page: https://github.com/behind24proxies/web-stats
Author: ICE-CREAM (Mike Lennon)
License: UNKNOWN
Keywords: python,website,website report,report,website performance,website stats
Platform: UNKNOWN
Classifier: Intended Audience :: Developers
Classifier: Programming Language :: Python :: 3
Classifier: Operating System :: Unix
Classifier: Operating System :: MacOS :: MacOS X
Classifier: Operating System :: Microsoft :: Windows
Requires-Dist: html-to-json
Requires-Dist: requests
Requires-Dist: time
Requires-Dist: warnings
